live_parquet/__init__.py
live_parquet/live_parquet_module.py
live_parquet-0.5.0.dist-info/METADATA
live_parquet-0.5.0.dist-info/WHEEL
live_parquet-0.5.0.dist-info/entry_points.txt
live_parquet-0.5.0.dist-info/top_level.txt
live_parquet-0.5.0.dist-info/RECORD
